py_telegram_bot/__init__.py
py_telegram_bot/bot.py
py_telegram_bot/exceptions.py
py_telegram_bot/keyboard.py
py_telegram_bot/uploader.py
py_telegram_bot-1.0.post3.dist-info/LICENSE
py_telegram_bot-1.0.post3.dist-info/METADATA
py_telegram_bot-1.0.post3.dist-info/WHEEL
py_telegram_bot-1.0.post3.dist-info/top_level.txt
py_telegram_bot-1.0.post3.dist-info/RECORD
