Metadata-Version: 2.1
Name: py-telegram-bot
Version: 1.0.post3
Summary: Telegram Bots API wrapper.
Home-page: https://gitlab.com/Nix13/telegram-api
Author: Nix13
Author-email: nix1304@gmail.com
License: UNKNOWN
Platform: UNKNOWN
Classifier: Programming Language :: Python :: 3
Classifier: License :: OSI Approved :: MIT License
Classifier: Operating System :: OS Independent
Requires-Dist: requests
Requires-Dist: pysocks
